{
  "epoch": {
    "steps": [
      0,
      9,
      19,
      29,
      39,
      49,
      59,
      69,
      79,
      89,
      99,
      109,
      119,
      129,
      139,
      149,
      159,
      169,
      179,
      189,
      199,
      209,
      219,
      229,
      239,
      249,
      259,
      269,
      279,
      289,
      299,
      309,
      319,
      329,
      339,
      349,
      359,
      369,
      379,
      389,
      399,
      409,
      419,
      429,
      439,
      449,
      459,
      469,
      479,
      489,
      499,
      509,
      519,
      529,
      539,
      549,
      559,
      569,
      579,
      589,
      599,
      609,
      619,
      629,
      639,
      649,
      659,
      669,
      679,
      689,
      699,
      709,
      719,
      729,
      739,
      749,
      759,
      769,
      779,
      789,
      799,
      809,
      819,
      829,
      839,
      849,
      859,
      869,
      879,
      889,
      899,
      909,
      919,
      929,
      939,
      949,
      959,
      969,
      979,
      989,
      999,
      1009,
      1019,
      1029,
      1039,
      1049,
      1059,
      1069,
      1079,
      1089,
      1099,
      1109,
      1119,
      1129,
      1139,
      1149,
      1159,
      1169,
      1179,
      1189,
      1199
    ],
    "timestamps": [
      "",
      "",
      "",
      "",
      "",
      "",
      "",
      "",
      "",
      "",
      "",
      "",
      "",
      "",
      "",
      "",
      "",
      "",
      "",
      "",
      "",
      "",
      "",
      "",
      "",
      "",
      "",
      "",
      "",
      "",
      "",
      "",
      "",
      "",
      "",
      "",
      "",
      "",
      "",
      "",
      "",
      "",
      "",
      "",
      "",
      "",
      "",
      "",
      "",
      "",
      "",
      "",
      "",
      "",
      "",
      "",
      "",
      "",
      "",
      "",
      "",
      "",
      "",
      "",
      "",
      "",
      "",
      "",
      "",
      "",
      "",
      "",
      "",
      "",
      "",
      "",
      "",
      "",
      "",
      "",
      "",
      "",
      "",
      "",
      "",
      "",
      "",
      "",
      "",
      "",
      "",
      "",
      "",
      "",
      "",
      "",
      "",
      "",
      "",
      "",
      "",
      "",
      "",
      "",
      "",
      "",
      "",
      "",
      "",
      "",
      "",
      "",
      "",
      "",
      "",
      "",
      "",
      "",
      "",
      "",
      ""
    ],
    "values": [
      0,
      9,
      19,
      29,
      39,
      49,
      59,
      69,
      79,
      89,
      99,
      109,
      119,
      129,
      139,
      149,
      159,
      169,
      179,
      189,
      199,
      209,
      219,
      229,
      239,
      249,
      259,
      269,
      279,
      289,
      299,
      309,
      319,
      329,
      339,
      349,
      359,
      369,
      379,
      389,
      399,
      409,
      419,
      429,
      439,
      449,
      459,
      469,
      479,
      489,
      499,
      509,
      519,
      529,
      539,
      549,
      559,
      569,
      579,
      589,
      599,
      609,
      619,
      629,
      639,
      649,
      659,
      669,
      679,
      689,
      699,
      709,
      719,
      729,
      739,
      749,
      759,
      769,
      779,
      789,
      799,
      809,
      819,
      829,
      839,
      849,
      859,
      869,
      879,
      889,
      899,
      909,
      919,
      929,
      939,
      949,
      959,
      969,
      979,
      989,
      999,
      1009,
      1019,
      1029,
      1039,
      1049,
      1059,
      1069,
      1079,
      1089,
      1099,
      1109,
      1119,
      1129,
      1139,
      1149,
      1159,
      1169,
      1179,
      1189,
      1199
    ]
  },
  "opex_average_return": {
    "steps": [
      0,
      9,
      19,
      29,
      39,
      49,
      59,
      69,
      79,
      89,
      99,
      109,
      119,
      129,
      139,
      149,
      159,
      169,
      179,
      189,
      199,
      209,
      219,
      229,
      239,
      249,
      259,
      269,
      279,
      289,
      299,
      309,
      319,
      329,
      339,
      349,
      359,
      369,
      379,
      389,
      399,
      409,
      419,
      429,
      439,
      449,
      459,
      469,
      479,
      489,
      499,
      509,
      519,
      529,
      539,
      549,
      559,
      569,
      579,
      589,
      599,
      609,
      619,
      629,
      639,
      649,
      659,
      669,
      679,
      689,
      699,
      709,
      719,
      729,
      739,
      749,
      759,
      769,
      779,
      789,
      799,
      809,
      819,
      829,
      839,
      849,
      859,
      869,
      879,
      889,
      899,
      909,
      919,
      929,
      939,
      949,
      959,
      969,
      979,
      989,
      999,
      1009,
      1019,
      1029,
      1039,
      1049,
      1059,
      1069,
      1079,
      1089,
      1099,
      1109,
      1119,
      1129,
      1139,
      1149,
      1159,
      1169,
      1179,
      1189,
      1199
    ],
    "timestamps": [
      "",
      "",
      "",
      "",
      "",
      "",
      "",
      "",
      "",
      "",
      "",
      "",
      "",
      "",
      "",
      "",
      "",
      "",
      "",
      "",
      "",
      "",
      "",
      "",
      "",
      "",
      "",
      "",
      "",
      "",
      "",
      "",
      "",
      "",
      "",
      "",
      "",
      "",
      "",
      "",
      "",
      "",
      "",
      "",
      "",
      "",
      "",
      "",
      "",
      "",
      "",
      "",
      "",
      "",
      "",
      "",
      "",
      "",
      "",
      "",
      "",
      "",
      "",
      "",
      "",
      "",
      "",
      "",
      "",
      "",
      "",
      "",
      "",
      "",
      "",
      "",
      "",
      "",
      "",
      "",
      "",
      "",
      "",
      "",
      "",
      "",
      "",
      "",
      "",
      "",
      "",
      "",
      "",
      "",
      "",
      "",
      "",
      "",
      "",
      "",
      "",
      "",
      "",
      "",
      "",
      "",
      "",
      "",
      "",
      "",
      "",
      "",
      "",
      "",
      "",
      "",
      "",
      "",
      "",
      "",
      ""
    ],
    "values": [
      0,
      0,
      0,
      0,
      0,
      0,
      0,
      0,
      0,
      0.009999999776482582,
      0,
      0.009999999776482582,
      0.03999999910593033,
      0.14000000059604645,
      0.10999999940395355,
      0.12999999523162842,
      0.30000001192092896,
      0.5400000214576721,
      0.7200000286102295,
      0.5600000023841858,
      0.5899999737739563,
      0.7099999785423279,
      0.41999998688697815,
      0.699999988079071,
      0.6000000238418579,
      0.5699999928474426,
      0.47999998927116394,
      0.44999998807907104,
      0.41999998688697815,
      0.6499999761581421,
      0.7099999785423279,
      0.6200000047683716,
      0.6600000262260437,
      0.550000011920929,
      0.5699999928474426,
      0.6499999761581421,
      0.44999998807907104,
      0.5899999737739563,
      0.6600000262260437,
      0.47999998927116394,
      0.3700000047683716,
      0.4000000059604645,
      0.44999998807907104,
      0.44999998807907104,
      0.7200000286102295,
      0.6100000143051147,
      0.4399999976158142,
      0.5299999713897705,
      0.46000000834465027,
      0.6200000047683716,
      0.5099999904632568,
      0.6100000143051147,
      0.5899999737739563,
      0.6399999856948853,
      0.6600000262260437,
      0.49000000953674316,
      0.6399999856948853,
      0.6299999952316284,
      0.6700000166893005,
      0.6200000047683716,
      0.7200000286102295,
      0.7200000286102295,
      0.7400000095367432,
      0.7300000190734863,
      0.75,
      0.7599999904632568,
      0.7300000190734863,
      0.7400000095367432,
      0.6700000166893005,
      0.7200000286102295,
      0.7799999713897705,
      0.7900000214576721,
      0.8299999833106995,
      0.8500000238418579,
      0.8600000143051147,
      0.8399999737739563,
      0.8500000238418579,
      0.8199999928474426,
      0.8299999833106995,
      0.8199999928474426,
      0.7900000214576721,
      0.8199999928474426,
      0.8299999833106995,
      0.8100000023841858,
      0.8399999737739563,
      0.8299999833106995,
      0.7699999809265137,
      0.7900000214576721,
      0.8700000047683716,
      0.8500000238418579,
      0.8500000238418579,
      0.8199999928474426,
      0.7900000214576721,
      0.8500000238418579,
      0.8600000143051147,
      0.7900000214576721,
      0.8199999928474426,
      0.7900000214576721,
      0.8899999856948853,
      0.8999999761581421,
      0.8600000143051147,
      0.8299999833106995,
      0.8199999928474426,
      0.8700000047683716,
      0.8299999833106995,
      0.7599999904632568,
      0.8500000238418579,
      0.8600000143051147,
      0.7900000214576721,
      0.7699999809265137,
      0.8100000023841858,
      0.8500000238418579,
      0.8700000047683716,
      0.800000011920929,
      0.8600000143051147,
      0.7799999713897705,
      0.8600000143051147,
      0.8299999833106995,
      0.8299999833106995,
      0.8799999952316284,
      0.8600000143051147
    ]
  },
  "eval_average_return": {
    "steps": [
      0,
      9,
      19,
      29,
      39,
      49,
      59,
      69,
      79,
      89,
      99,
      109,
      119,
      129,
      139,
      149,
      159,
      169,
      179,
      189,
      199,
      209,
      219,
      229,
      239,
      249,
      259,
      269,
      279,
      289,
      299,
      309,
      319,
      329,
      339,
      349,
      359,
      369,
      379,
      389,
      399,
      409,
      419,
      429,
      439,
      449,
      459,
      469,
      479,
      489,
      499,
      509,
      519,
      529,
      539,
      549,
      559,
      569,
      579,
      589,
      599,
      609,
      619,
      629,
      639,
      649,
      659,
      669,
      679,
      689,
      699,
      709,
      719,
      729,
      739,
      749,
      759,
      769,
      779,
      789,
      799,
      809,
      819,
      829,
      839,
      849,
      859,
      869,
      879,
      889,
      899,
      909,
      919,
      929,
      939,
      949,
      959,
      969,
      979,
      989,
      999,
      1009,
      1019,
      1029,
      1039,
      1049,
      1059,
      1069,
      1079,
      1089,
      1099,
      1109,
      1119,
      1129,
      1139,
      1149,
      1159,
      1169,
      1179,
      1189,
      1199
    ],
    "timestamps": [
      "",
      "",
      "",
      "",
      "",
      "",
      "",
      "",
      "",
      "",
      "",
      "",
      "",
      "",
      "",
      "",
      "",
      "",
      "",
      "",
      "",
      "",
      "",
      "",
      "",
      "",
      "",
      "",
      "",
      "",
      "",
      "",
      "",
      "",
      "",
      "",
      "",
      "",
      "",
      "",
      "",
      "",
      "",
      "",
      "",
      "",
      "",
      "",
      "",
      "",
      "",
      "",
      "",
      "",
      "",
      "",
      "",
      "",
      "",
      "",
      "",
      "",
      "",
      "",
      "",
      "",
      "",
      "",
      "",
      "",
      "",
      "",
      "",
      "",
      "",
      "",
      "",
      "",
      "",
      "",
      "",
      "",
      "",
      "",
      "",
      "",
      "",
      "",
      "",
      "",
      "",
      "",
      "",
      "",
      "",
      "",
      "",
      "",
      "",
      "",
      "",
      "",
      "",
      "",
      "",
      "",
      "",
      "",
      "",
      "",
      "",
      "",
      "",
      "",
      "",
      "",
      "",
      "",
      "",
      "",
      ""
    ],
    "values": [
      0,
      0,
      0,
      0,
      0,
      0,
      0,
      0,
      0,
      0,
      0,
      0,
      0,
      0.07000000029802322,
      0.009999999776482582,
      0.009999999776482582,
      0.23999999463558197,
      0.36000001430511475,
      0.41999998688697815,
      0.5600000023841858,
      0.38999998569488525,
      0.6499999761581421,
      0.27000001072883606,
      0.550000011920929,
      0.6299999952316284,
      0.3100000023841858,
      0.4300000071525574,
      0.3400000035762787,
      0.4000000059604645,
      0.5899999737739563,
      0.550000011920929,
      0.41999998688697815,
      0.46000000834465027,
      0.5,
      0.49000000953674316,
      0.49000000953674316,
      0.3499999940395355,
      0.44999998807907104,
      0.5600000023841858,
      0.3700000047683716,
      0.27000001072883606,
      0.3199999928474426,
      0.3400000035762787,
      0.3799999952316284,
      0.6600000262260437,
      0.41999998688697815,
      0.33000001311302185,
      0.3799999952316284,
      0.6800000071525574,
      0.6499999761581421,
      0.5600000023841858,
      0.5799999833106995,
      0.5199999809265137,
      0.6000000238418579,
      0.6399999856948853,
      0.4699999988079071,
      0.699999988079071,
      0.5799999833106995,
      0.6200000047683716,
      0.5699999928474426,
      0.7099999785423279,
      0.6600000262260437,
      0.7099999785423279,
      0.7099999785423279,
      0.7099999785423279,
      0.7300000190734863,
      0.6299999952316284,
      0.6899999976158142,
      0.6399999856948853,
      0.6800000071525574,
      0.6299999952316284,
      0.6200000047683716,
      0.6000000238418579,
      0.6899999976158142,
      0.7099999785423279,
      0.5600000023841858,
      0.7099999785423279,
      0.7900000214576721,
      0.6800000071525574,
      0.699999988079071,
      0.7300000190734863,
      0.7099999785423279,
      0.75,
      0.7300000190734863,
      0.699999988079071,
      0.7599999904632568,
      0.75,
      0.7699999809265137,
      0.7099999785423279,
      0.699999988079071,
      0.800000011920929,
      0.7300000190734863,
      0.7099999785423279,
      0.7099999785423279,
      0.6600000262260437,
      0.6200000047683716,
      0.699999988079071,
      0.6299999952316284,
      0.6499999761581421,
      0.699999988079071,
      0.7799999713897705,
      0.6499999761581421,
      0.7300000190734863,
      0.7300000190734863,
      0.6100000143051147,
      0.6399999856948853,
      0.6600000262260437,
      0.6000000238418579,
      0.7599999904632568,
      0.7599999904632568,
      0.6200000047683716,
      0.6600000262260437,
      0.6700000166893005,
      0.7599999904632568,
      0.6600000262260437,
      0.7400000095367432,
      0.6399999856948853,
      0.6100000143051147,
      0.6600000262260437,
      0.6299999952316284,
      0.6200000047683716
    ]
  },
  "action_gap": {
    "steps": [
      0,
      9,
      19,
      29,
      39,
      49,
      59,
      69,
      79,
      89,
      99,
      109,
      119,
      129,
      139,
      149,
      159,
      169,
      179,
      189,
      199,
      209,
      219,
      229,
      239,
      249,
      259,
      269,
      279,
      289,
      299,
      309,
      319,
      329,
      339,
      349,
      359,
      369,
      379,
      389,
      399,
      409,
      419,
      429,
      439,
      449,
      459,
      469,
      479,
      489,
      499,
      509,
      519,
      529,
      539,
      549,
      559,
      569,
      579,
      589,
      599,
      609,
      619,
      629,
      639,
      649,
      659,
      669,
      679,
      689,
      699,
      709,
      719,
      729,
      739,
      749,
      759,
      769,
      779,
      789,
      799,
      809,
      819,
      829,
      839,
      849,
      859,
      869,
      879,
      889,
      899,
      909,
      919,
      929,
      939,
      949,
      959,
      969,
      979,
      989,
      999,
      1009,
      1019,
      1029,
      1039,
      1049,
      1059,
      1069,
      1079,
      1089,
      1099,
      1109,
      1119,
      1129,
      1139,
      1149,
      1159,
      1169,
      1179,
      1189,
      1199
    ],
    "timestamps": [
      "",
      "",
      "",
      "",
      "",
      "",
      "",
      "",
      "",
      "",
      "",
      "",
      "",
      "",
      "",
      "",
      "",
      "",
      "",
      "",
      "",
      "",
      "",
      "",
      "",
      "",
      "",
      "",
      "",
      "",
      "",
      "",
      "",
      "",
      "",
      "",
      "",
      "",
      "",
      "",
      "",
      "",
      "",
      "",
      "",
      "",
      "",
      "",
      "",
      "",
      "",
      "",
      "",
      "",
      "",
      "",
      "",
      "",
      "",
      "",
      "",
      "",
      "",
      "",
      "",
      "",
      "",
      "",
      "",
      "",
      "",
      "",
      "",
      "",
      "",
      "",
      "",
      "",
      "",
      "",
      "",
      "",
      "",
      "",
      "",
      "",
      "",
      "",
      "",
      "",
      "",
      "",
      "",
      "",
      "",
      "",
      "",
      "",
      "",
      "",
      "",
      "",
      "",
      "",
      "",
      "",
      "",
      "",
      "",
      "",
      "",
      "",
      "",
      "",
      "",
      "",
      "",
      "",
      "",
      "",
      ""
    ],
    "values": [
      3.0890374183654785,
      2.5699822902679443,
      2.5557398796081543,
      2.4817521572113037,
      2.5880281925201416,
      2.639587640762329,
      2.6515486240386963,
      2.7712502479553223,
      2.7859981060028076,
      2.6621217727661133,
      2.832862615585327,
      2.8904454708099365,
      2.793191432952881,
      2.821894884109497,
      2.777188777923584,
      2.6788711547851562,
      2.8728857040405273,
      2.7881298065185547,
      2.8127341270446777,
      2.733438491821289,
      2.8424158096313477,
      2.7649505138397217,
      2.716268301010132,
      2.8046278953552246,
      2.775385856628418,
      2.8067290782928467,
      2.8511922359466553,
      2.775491952896118,
      2.7076456546783447,
      2.7399346828460693,
      2.8145225048065186,
      2.665693759918213,
      2.8448073863983154,
      2.807084560394287,
      2.781240463256836,
      2.8752851486206055,
      2.7122488021850586,
      2.798103094100952,
      2.751347541809082,
      2.775689125061035,
      2.6947710514068604,
      2.9260940551757812,
      2.7115089893341064,
      2.6779041290283203,
      2.822260856628418,
      2.663466691970825,
      2.820382595062256,
      2.644618511199951,
      2.7908191680908203,
      2.7123541831970215,
      2.8564319610595703,
      2.7961316108703613,
      2.7840545177459717,
      2.7913811206817627,
      2.8200197219848633,
      2.8427915573120117,
      2.82646107673645,
      2.7577409744262695,
      2.6916260719299316,
      2.740161657333374,
      2.913585901260376,
      2.780067205429077,
      2.762052297592163,
      2.806292772293091,
      2.8805758953094482,
      2.7893974781036377,
      2.798280954360962,
      2.837242364883423,
      2.8080217838287354,
      2.8524062633514404,
      2.767504930496216,
      2.9305243492126465,
      2.812774419784546,
      2.8761212825775146,
      2.908919095993042,
      2.912531852722168,
      2.9288086891174316,
      2.937432289123535,
      2.911959648132324,
      2.8854990005493164,
      2.921292304992676,
      2.854896306991577,
      2.857726812362671,
      2.8651740550994873,
      2.8883609771728516,
      2.8915297985076904,
      2.86948299407959,
      3.0083510875701904,
      2.9313278198242188,
      2.918044328689575,
      2.8653125762939453,
      2.8046224117279053,
      2.977449893951416,
      2.9174630641937256,
      2.93135142326355,
      2.973816156387329,
      2.8574037551879883,
      2.9087352752685547,
      2.969467878341675,
      2.8943424224853516,
      2.919296979904175,
      2.9983913898468018,
      2.9281888008117676,
      2.916412591934204,
      2.8886687755584717,
      3.01363468170166,
      2.9027578830718994,
      2.9295053482055664,
      2.9318652153015137,
      2.912555456161499,
      2.942708730697632,
      2.962398052215576,
      2.9626247882843018,
      2.951085090637207,
      2.8807263374328613,
      2.947314500808716,
      2.9547557830810547,
      2.8647711277008057,
      2.910264015197754,
      2.951817035675049,
      2.9043984413146973
    ]
  }
}