{
  "epoch": {
    "steps": [
      0,
      9,
      19,
      29,
      39,
      49,
      59,
      69,
      79,
      89,
      99,
      109,
      119,
      129,
      139,
      149,
      159,
      169,
      179,
      189,
      199,
      209,
      219,
      229,
      239,
      249,
      259,
      269,
      279,
      289,
      299,
      309,
      319,
      329,
      339,
      349,
      359,
      369,
      379,
      389,
      399,
      409,
      419,
      429,
      439,
      449,
      459,
      469,
      479,
      489,
      499,
      509,
      519,
      529,
      539,
      549,
      559,
      569,
      579,
      589,
      599,
      609,
      619,
      629,
      639,
      649,
      659,
      669,
      679,
      689,
      699,
      709,
      719,
      729,
      739,
      749,
      759,
      769,
      779,
      789,
      799,
      809,
      819,
      829,
      839,
      849,
      859,
      869,
      879,
      889,
      899,
      909,
      919,
      929,
      939,
      949,
      959,
      969,
      979,
      989,
      999,
      1009,
      1019,
      1029,
      1039,
      1049,
      1059,
      1069,
      1079,
      1089,
      1099,
      1109,
      1119,
      1129,
      1139,
      1149,
      1159,
      1169,
      1179,
      1189,
      1199
    ],
    "timestamps": [
      "",
      "",
      "",
      "",
      "",
      "",
      "",
      "",
      "",
      "",
      "",
      "",
      "",
      "",
      "",
      "",
      "",
      "",
      "",
      "",
      "",
      "",
      "",
      "",
      "",
      "",
      "",
      "",
      "",
      "",
      "",
      "",
      "",
      "",
      "",
      "",
      "",
      "",
      "",
      "",
      "",
      "",
      "",
      "",
      "",
      "",
      "",
      "",
      "",
      "",
      "",
      "",
      "",
      "",
      "",
      "",
      "",
      "",
      "",
      "",
      "",
      "",
      "",
      "",
      "",
      "",
      "",
      "",
      "",
      "",
      "",
      "",
      "",
      "",
      "",
      "",
      "",
      "",
      "",
      "",
      "",
      "",
      "",
      "",
      "",
      "",
      "",
      "",
      "",
      "",
      "",
      "",
      "",
      "",
      "",
      "",
      "",
      "",
      "",
      "",
      "",
      "",
      "",
      "",
      "",
      "",
      "",
      "",
      "",
      "",
      "",
      "",
      "",
      "",
      "",
      "",
      "",
      "",
      "",
      "",
      ""
    ],
    "values": [
      0,
      9,
      19,
      29,
      39,
      49,
      59,
      69,
      79,
      89,
      99,
      109,
      119,
      129,
      139,
      149,
      159,
      169,
      179,
      189,
      199,
      209,
      219,
      229,
      239,
      249,
      259,
      269,
      279,
      289,
      299,
      309,
      319,
      329,
      339,
      349,
      359,
      369,
      379,
      389,
      399,
      409,
      419,
      429,
      439,
      449,
      459,
      469,
      479,
      489,
      499,
      509,
      519,
      529,
      539,
      549,
      559,
      569,
      579,
      589,
      599,
      609,
      619,
      629,
      639,
      649,
      659,
      669,
      679,
      689,
      699,
      709,
      719,
      729,
      739,
      749,
      759,
      769,
      779,
      789,
      799,
      809,
      819,
      829,
      839,
      849,
      859,
      869,
      879,
      889,
      899,
      909,
      919,
      929,
      939,
      949,
      959,
      969,
      979,
      989,
      999,
      1009,
      1019,
      1029,
      1039,
      1049,
      1059,
      1069,
      1079,
      1089,
      1099,
      1109,
      1119,
      1129,
      1139,
      1149,
      1159,
      1169,
      1179,
      1189,
      1199
    ]
  },
  "opex_average_return": {
    "steps": [
      0,
      9,
      19,
      29,
      39,
      49,
      59,
      69,
      79,
      89,
      99,
      109,
      119,
      129,
      139,
      149,
      159,
      169,
      179,
      189,
      199,
      209,
      219,
      229,
      239,
      249,
      259,
      269,
      279,
      289,
      299,
      309,
      319,
      329,
      339,
      349,
      359,
      369,
      379,
      389,
      399,
      409,
      419,
      429,
      439,
      449,
      459,
      469,
      479,
      489,
      499,
      509,
      519,
      529,
      539,
      549,
      559,
      569,
      579,
      589,
      599,
      609,
      619,
      629,
      639,
      649,
      659,
      669,
      679,
      689,
      699,
      709,
      719,
      729,
      739,
      749,
      759,
      769,
      779,
      789,
      799,
      809,
      819,
      829,
      839,
      849,
      859,
      869,
      879,
      889,
      899,
      909,
      919,
      929,
      939,
      949,
      959,
      969,
      979,
      989,
      999,
      1009,
      1019,
      1029,
      1039,
      1049,
      1059,
      1069,
      1079,
      1089,
      1099,
      1109,
      1119,
      1129,
      1139,
      1149,
      1159,
      1169,
      1179,
      1189,
      1199
    ],
    "timestamps": [
      "",
      "",
      "",
      "",
      "",
      "",
      "",
      "",
      "",
      "",
      "",
      "",
      "",
      "",
      "",
      "",
      "",
      "",
      "",
      "",
      "",
      "",
      "",
      "",
      "",
      "",
      "",
      "",
      "",
      "",
      "",
      "",
      "",
      "",
      "",
      "",
      "",
      "",
      "",
      "",
      "",
      "",
      "",
      "",
      "",
      "",
      "",
      "",
      "",
      "",
      "",
      "",
      "",
      "",
      "",
      "",
      "",
      "",
      "",
      "",
      "",
      "",
      "",
      "",
      "",
      "",
      "",
      "",
      "",
      "",
      "",
      "",
      "",
      "",
      "",
      "",
      "",
      "",
      "",
      "",
      "",
      "",
      "",
      "",
      "",
      "",
      "",
      "",
      "",
      "",
      "",
      "",
      "",
      "",
      "",
      "",
      "",
      "",
      "",
      "",
      "",
      "",
      "",
      "",
      "",
      "",
      "",
      "",
      "",
      "",
      "",
      "",
      "",
      "",
      "",
      "",
      "",
      "",
      "",
      "",
      ""
    ],
    "values": [
      0,
      0,
      0,
      0,
      0.550000011920929,
      0.6200000047683716,
      0.75,
      0.7099999785423279,
      0.41999998688697815,
      0.6100000143051147,
      0.550000011920929,
      0.6499999761581421,
      0.6100000143051147,
      0.5899999737739563,
      0.6800000071525574,
      0.8100000023841858,
      0.7699999809265137,
      0.7599999904632568,
      0.6899999976158142,
      0.800000011920929,
      0.800000011920929,
      0.9100000262260437,
      0.7599999904632568,
      0.800000011920929,
      0.8199999928474426,
      0.8299999833106995,
      0.7300000190734863,
      0.7300000190734863,
      0.8999999761581421,
      0.7099999785423279,
      0.8399999737739563,
      0.8399999737739563,
      0.8100000023841858,
      0.7900000214576721,
      0.800000011920929,
      0.8100000023841858,
      0.7400000095367432,
      0.7799999713897705,
      0.7699999809265137,
      0.7699999809265137,
      0.8399999737739563,
      0.6800000071525574,
      0.8299999833106995,
      0.8299999833106995,
      0.7900000214576721,
      0.8600000143051147,
      0.7400000095367432,
      0.7300000190734863,
      0.8399999737739563,
      0.7599999904632568,
      0.8500000238418579,
      0.6899999976158142,
      0.7699999809265137,
      0.9100000262260437,
      0.7599999904632568,
      0.7900000214576721,
      0.800000011920929,
      0.8100000023841858,
      0.75,
      0.8799999952316284,
      0.8299999833106995,
      0.8199999928474426,
      0.7699999809265137,
      0.800000011920929,
      0.7900000214576721,
      0.8299999833106995,
      0.7799999713897705,
      0.7300000190734863,
      0.8399999737739563,
      0.800000011920929,
      0.8100000023841858,
      0.800000011920929,
      0.8299999833106995,
      0.8500000238418579,
      0.8899999856948853,
      0.8600000143051147,
      0.8399999737739563,
      0.8600000143051147,
      0.8100000023841858,
      0.9200000166893005,
      0.8899999856948853,
      0.8500000238418579,
      0.8600000143051147,
      0.7900000214576721,
      0.8500000238418579,
      0.8399999737739563,
      0.800000011920929,
      0.8899999856948853,
      0.8700000047683716,
      0.8299999833106995,
      0.8600000143051147,
      0.8799999952316284,
      0.8299999833106995,
      0.8199999928474426,
      0.8600000143051147,
      0.8600000143051147,
      0.8899999856948853,
      0.8899999856948853,
      0.8100000023841858,
      0.8799999952316284,
      0.8500000238418579,
      0.8299999833106995,
      0.8899999856948853,
      0.8399999737739563,
      0.8799999952316284,
      0.8700000047683716,
      0.8799999952316284,
      0.9100000262260437,
      0.8899999856948853,
      0.7799999713897705,
      0.8700000047683716,
      0.9100000262260437,
      0.8999999761581421,
      0.8600000143051147,
      0.9399999976158142,
      0.8500000238418579,
      0.8600000143051147,
      0.8500000238418579,
      0.8600000143051147,
      0.8700000047683716,
      0.9399999976158142
    ]
  },
  "eval_average_return": {
    "steps": [
      0,
      9,
      19,
      29,
      39,
      49,
      59,
      69,
      79,
      89,
      99,
      109,
      119,
      129,
      139,
      149,
      159,
      169,
      179,
      189,
      199,
      209,
      219,
      229,
      239,
      249,
      259,
      269,
      279,
      289,
      299,
      309,
      319,
      329,
      339,
      349,
      359,
      369,
      379,
      389,
      399,
      409,
      419,
      429,
      439,
      449,
      459,
      469,
      479,
      489,
      499,
      509,
      519,
      529,
      539,
      549,
      559,
      569,
      579,
      589,
      599,
      609,
      619,
      629,
      639,
      649,
      659,
      669,
      679,
      689,
      699,
      709,
      719,
      729,
      739,
      749,
      759,
      769,
      779,
      789,
      799,
      809,
      819,
      829,
      839,
      849,
      859,
      869,
      879,
      889,
      899,
      909,
      919,
      929,
      939,
      949,
      959,
      969,
      979,
      989,
      999,
      1009,
      1019,
      1029,
      1039,
      1049,
      1059,
      1069,
      1079,
      1089,
      1099,
      1109,
      1119,
      1129,
      1139,
      1149,
      1159,
      1169,
      1179,
      1189,
      1199
    ],
    "timestamps": [
      "",
      "",
      "",
      "",
      "",
      "",
      "",
      "",
      "",
      "",
      "",
      "",
      "",
      "",
      "",
      "",
      "",
      "",
      "",
      "",
      "",
      "",
      "",
      "",
      "",
      "",
      "",
      "",
      "",
      "",
      "",
      "",
      "",
      "",
      "",
      "",
      "",
      "",
      "",
      "",
      "",
      "",
      "",
      "",
      "",
      "",
      "",
      "",
      "",
      "",
      "",
      "",
      "",
      "",
      "",
      "",
      "",
      "",
      "",
      "",
      "",
      "",
      "",
      "",
      "",
      "",
      "",
      "",
      "",
      "",
      "",
      "",
      "",
      "",
      "",
      "",
      "",
      "",
      "",
      "",
      "",
      "",
      "",
      "",
      "",
      "",
      "",
      "",
      "",
      "",
      "",
      "",
      "",
      "",
      "",
      "",
      "",
      "",
      "",
      "",
      "",
      "",
      "",
      "",
      "",
      "",
      "",
      "",
      "",
      "",
      "",
      "",
      "",
      "",
      "",
      "",
      "",
      "",
      "",
      "",
      ""
    ],
    "values": [
      0,
      0,
      0,
      0,
      0.46000000834465027,
      0.5,
      0.46000000834465027,
      0.4699999988079071,
      0.5099999904632568,
      0.47999998927116394,
      0.5,
      0.5299999713897705,
      0.5299999713897705,
      0.5099999904632568,
      0.6000000238418579,
      0.6399999856948853,
      0.5299999713897705,
      0.6200000047683716,
      0.7200000286102295,
      0.6200000047683716,
      0.7900000214576721,
      0.8100000023841858,
      0.7799999713897705,
      0.6299999952316284,
      0.6299999952316284,
      0.6499999761581421,
      0.6399999856948853,
      0.6299999952316284,
      0.7599999904632568,
      0.6800000071525574,
      0.7900000214576721,
      0.7300000190734863,
      0.5699999928474426,
      0.6499999761581421,
      0.5699999928474426,
      0.6299999952316284,
      0.5099999904632568,
      0.6600000262260437,
      0.6399999856948853,
      0.7099999785423279,
      0.6600000262260437,
      0.6899999976158142,
      0.699999988079071,
      0.5899999737739563,
      0.6000000238418579,
      0.7099999785423279,
      0.5799999833106995,
      0.6600000262260437,
      0.7300000190734863,
      0.7300000190734863,
      0.6499999761581421,
      0.7200000286102295,
      0.75,
      0.7099999785423279,
      0.6000000238418579,
      0.7099999785423279,
      0.8100000023841858,
      0.7400000095367432,
      0.6399999856948853,
      0.6499999761581421,
      0.6600000262260437,
      0.6899999976158142,
      0.6000000238418579,
      0.7799999713897705,
      0.6700000166893005,
      0.75,
      0.7400000095367432,
      0.5899999737739563,
      0.7099999785423279,
      0.6899999976158142,
      0.7400000095367432,
      0.6700000166893005,
      0.6800000071525574,
      0.7099999785423279,
      0.699999988079071,
      0.6399999856948853,
      0.7599999904632568,
      0.7799999713897705,
      0.75,
      0.75,
      0.6899999976158142,
      0.7900000214576721,
      0.6499999761581421,
      0.7300000190734863,
      0.8199999928474426,
      0.7799999713897705,
      0.7099999785423279,
      0.8299999833106995,
      0.7699999809265137,
      0.7900000214576721,
      0.6600000262260437,
      0.6800000071525574,
      0.7200000286102295,
      0.75,
      0.7599999904632568,
      0.7200000286102295,
      0.75,
      0.7300000190734863,
      0.699999988079071,
      0.75,
      0.7400000095367432,
      0.7300000190734863,
      0.6299999952316284,
      0.6700000166893005,
      0.7200000286102295,
      0.6800000071525574,
      0.7900000214576721,
      0.7300000190734863,
      0.7300000190734863,
      0.75,
      0.7099999785423279,
      0.7099999785423279,
      0.7200000286102295,
      0.7599999904632568,
      0.75,
      0.6899999976158142,
      0.6899999976158142,
      0.7400000095367432,
      0.7599999904632568,
      0.7599999904632568,
      0.7699999809265137
    ]
  },
  "action_gap": {
    "steps": [
      0,
      9,
      19,
      29,
      39,
      49,
      59,
      69,
      79,
      89,
      99,
      109,
      119,
      129,
      139,
      149,
      159,
      169,
      179,
      189,
      199,
      209,
      219,
      229,
      239,
      249,
      259,
      269,
      279,
      289,
      299,
      309,
      319,
      329,
      339,
      349,
      359,
      369,
      379,
      389,
      399,
      409,
      419,
      429,
      439,
      449,
      459,
      469,
      479,
      489,
      499,
      509,
      519,
      529,
      539,
      549,
      559,
      569,
      579,
      589,
      599,
      609,
      619,
      629,
      639,
      649,
      659,
      669,
      679,
      689,
      699,
      709,
      719,
      729,
      739,
      749,
      759,
      769,
      779,
      789,
      799,
      809,
      819,
      829,
      839,
      849,
      859,
      869,
      879,
      889,
      899,
      909,
      919,
      929,
      939,
      949,
      959,
      969,
      979,
      989,
      999,
      1009,
      1019,
      1029,
      1039,
      1049,
      1059,
      1069,
      1079,
      1089,
      1099,
      1109,
      1119,
      1129,
      1139,
      1149,
      1159,
      1169,
      1179,
      1189,
      1199
    ],
    "timestamps": [
      "",
      "",
      "",
      "",
      "",
      "",
      "",
      "",
      "",
      "",
      "",
      "",
      "",
      "",
      "",
      "",
      "",
      "",
      "",
      "",
      "",
      "",
      "",
      "",
      "",
      "",
      "",
      "",
      "",
      "",
      "",
      "",
      "",
      "",
      "",
      "",
      "",
      "",
      "",
      "",
      "",
      "",
      "",
      "",
      "",
      "",
      "",
      "",
      "",
      "",
      "",
      "",
      "",
      "",
      "",
      "",
      "",
      "",
      "",
      "",
      "",
      "",
      "",
      "",
      "",
      "",
      "",
      "",
      "",
      "",
      "",
      "",
      "",
      "",
      "",
      "",
      "",
      "",
      "",
      "",
      "",
      "",
      "",
      "",
      "",
      "",
      "",
      "",
      "",
      "",
      "",
      "",
      "",
      "",
      "",
      "",
      "",
      "",
      "",
      "",
      "",
      "",
      "",
      "",
      "",
      "",
      "",
      "",
      "",
      "",
      "",
      "",
      "",
      "",
      "",
      "",
      "",
      "",
      "",
      "",
      ""
    ],
    "values": [
      3.112440347671509,
      2.336526393890381,
      2.401954174041748,
      2.480886459350586,
      2.5583600997924805,
      2.6019864082336426,
      2.6716911792755127,
      2.742767572402954,
      2.7813985347747803,
      2.810519218444824,
      2.8796584606170654,
      2.7641353607177734,
      2.7851648330688477,
      2.876513719558716,
      2.8901243209838867,
      2.847790002822876,
      2.9185667037963867,
      2.9154601097106934,
      2.8623616695404053,
      2.7912161350250244,
      2.8151369094848633,
      2.8102853298187256,
      2.7924797534942627,
      2.9000136852264404,
      2.900768518447876,
      2.8272922039031982,
      2.900552988052368,
      2.9182631969451904,
      2.802145004272461,
      2.8529086112976074,
      2.8306801319122314,
      2.8552675247192383,
      2.8300280570983887,
      2.9148952960968018,
      2.7796716690063477,
      2.88278865814209,
      2.9294087886810303,
      2.801894187927246,
      2.9543628692626953,
      2.861208915710449,
      2.787809133529663,
      2.913806676864624,
      2.8700952529907227,
      2.8887939453125,
      2.880378484725952,
      2.895834445953369,
      2.9199295043945312,
      2.8506076335906982,
      2.9064035415649414,
      2.8111026287078857,
      2.8771536350250244,
      2.8970906734466553,
      2.915717124938965,
      2.772594928741455,
      2.93064022064209,
      2.888207197189331,
      2.904456853866577,
      2.9431252479553223,
      2.875786781311035,
      2.8690078258514404,
      2.9167892932891846,
      2.860327959060669,
      2.907186985015869,
      2.852803945541382,
      2.8863022327423096,
      2.905336856842041,
      2.910569190979004,
      2.9098458290100098,
      2.8849942684173584,
      2.8576018810272217,
      2.9473373889923096,
      2.8934109210968018,
      2.884310722351074,
      2.821061372756958,
      2.8195929527282715,
      2.8843495845794678,
      2.8770875930786133,
      2.9494783878326416,
      2.875528573989868,
      2.855114459991455,
      2.791435956954956,
      2.9241907596588135,
      2.872288465499878,
      2.8544833660125732,
      2.8723795413970947,
      2.8794498443603516,
      2.9596939086914062,
      2.8666598796844482,
      2.8980941772460938,
      2.9753918647766113,
      2.8840975761413574,
      2.84041166305542,
      2.876810312271118,
      2.9306838512420654,
      2.922898530960083,
      2.885152578353882,
      2.890432119369507,
      2.7978744506835938,
      2.895556926727295,
      2.9083662033081055,
      2.8816275596618652,
      2.881115436553955,
      2.909348964691162,
      2.9669878482818604,
      2.8913817405700684,
      2.9745492935180664,
      2.870844841003418,
      2.8559250831604004,
      3.025938034057617,
      2.896732807159424,
      2.901607036590576,
      2.8785691261291504,
      2.8548696041107178,
      2.879506826400757,
      2.8203537464141846,
      2.8304009437561035,
      2.904465675354004,
      2.8892581462860107,
      2.9460954666137695,
      2.853675127029419,
      2.8590199947357178
    ]
  }
}