{
  "epoch": {
    "steps": [
      0,
      9,
      19,
      29,
      39,
      49,
      59,
      69,
      79,
      89,
      99,
      109,
      119,
      129,
      139,
      149,
      159,
      169,
      179,
      189,
      199,
      209,
      219,
      229,
      239,
      249,
      259,
      269,
      279,
      289,
      299,
      309,
      319,
      329,
      339,
      349,
      359,
      369,
      379,
      389,
      399,
      409,
      419,
      429,
      439,
      449,
      459,
      469,
      479,
      489,
      499,
      509,
      519,
      529,
      539,
      549,
      559,
      569,
      579,
      589,
      599,
      609,
      619,
      629,
      639,
      649,
      659,
      669,
      679,
      689,
      699,
      709,
      719,
      729,
      739,
      749,
      759,
      769,
      779,
      789,
      799,
      809,
      819,
      829,
      839,
      849,
      859,
      869,
      879,
      889,
      899,
      909,
      919,
      929,
      939,
      949,
      959,
      969,
      979,
      989,
      999,
      1009,
      1019,
      1029,
      1039,
      1049,
      1059,
      1069,
      1079,
      1089,
      1099,
      1109,
      1119,
      1129,
      1139,
      1149,
      1159,
      1169,
      1179,
      1189,
      1199
    ],
    "timestamps": [
      "",
      "",
      "",
      "",
      "",
      "",
      "",
      "",
      "",
      "",
      "",
      "",
      "",
      "",
      "",
      "",
      "",
      "",
      "",
      "",
      "",
      "",
      "",
      "",
      "",
      "",
      "",
      "",
      "",
      "",
      "",
      "",
      "",
      "",
      "",
      "",
      "",
      "",
      "",
      "",
      "",
      "",
      "",
      "",
      "",
      "",
      "",
      "",
      "",
      "",
      "",
      "",
      "",
      "",
      "",
      "",
      "",
      "",
      "",
      "",
      "",
      "",
      "",
      "",
      "",
      "",
      "",
      "",
      "",
      "",
      "",
      "",
      "",
      "",
      "",
      "",
      "",
      "",
      "",
      "",
      "",
      "",
      "",
      "",
      "",
      "",
      "",
      "",
      "",
      "",
      "",
      "",
      "",
      "",
      "",
      "",
      "",
      "",
      "",
      "",
      "",
      "",
      "",
      "",
      "",
      "",
      "",
      "",
      "",
      "",
      "",
      "",
      "",
      "",
      "",
      "",
      "",
      "",
      "",
      "",
      ""
    ],
    "values": [
      0,
      9,
      19,
      29,
      39,
      49,
      59,
      69,
      79,
      89,
      99,
      109,
      119,
      129,
      139,
      149,
      159,
      169,
      179,
      189,
      199,
      209,
      219,
      229,
      239,
      249,
      259,
      269,
      279,
      289,
      299,
      309,
      319,
      329,
      339,
      349,
      359,
      369,
      379,
      389,
      399,
      409,
      419,
      429,
      439,
      449,
      459,
      469,
      479,
      489,
      499,
      509,
      519,
      529,
      539,
      549,
      559,
      569,
      579,
      589,
      599,
      609,
      619,
      629,
      639,
      649,
      659,
      669,
      679,
      689,
      699,
      709,
      719,
      729,
      739,
      749,
      759,
      769,
      779,
      789,
      799,
      809,
      819,
      829,
      839,
      849,
      859,
      869,
      879,
      889,
      899,
      909,
      919,
      929,
      939,
      949,
      959,
      969,
      979,
      989,
      999,
      1009,
      1019,
      1029,
      1039,
      1049,
      1059,
      1069,
      1079,
      1089,
      1099,
      1109,
      1119,
      1129,
      1139,
      1149,
      1159,
      1169,
      1179,
      1189,
      1199
    ]
  },
  "opex_average_return": {
    "steps": [
      0,
      9,
      19,
      29,
      39,
      49,
      59,
      69,
      79,
      89,
      99,
      109,
      119,
      129,
      139,
      149,
      159,
      169,
      179,
      189,
      199,
      209,
      219,
      229,
      239,
      249,
      259,
      269,
      279,
      289,
      299,
      309,
      319,
      329,
      339,
      349,
      359,
      369,
      379,
      389,
      399,
      409,
      419,
      429,
      439,
      449,
      459,
      469,
      479,
      489,
      499,
      509,
      519,
      529,
      539,
      549,
      559,
      569,
      579,
      589,
      599,
      609,
      619,
      629,
      639,
      649,
      659,
      669,
      679,
      689,
      699,
      709,
      719,
      729,
      739,
      749,
      759,
      769,
      779,
      789,
      799,
      809,
      819,
      829,
      839,
      849,
      859,
      869,
      879,
      889,
      899,
      909,
      919,
      929,
      939,
      949,
      959,
      969,
      979,
      989,
      999,
      1009,
      1019,
      1029,
      1039,
      1049,
      1059,
      1069,
      1079,
      1089,
      1099,
      1109,
      1119,
      1129,
      1139,
      1149,
      1159,
      1169,
      1179,
      1189,
      1199
    ],
    "timestamps": [
      "",
      "",
      "",
      "",
      "",
      "",
      "",
      "",
      "",
      "",
      "",
      "",
      "",
      "",
      "",
      "",
      "",
      "",
      "",
      "",
      "",
      "",
      "",
      "",
      "",
      "",
      "",
      "",
      "",
      "",
      "",
      "",
      "",
      "",
      "",
      "",
      "",
      "",
      "",
      "",
      "",
      "",
      "",
      "",
      "",
      "",
      "",
      "",
      "",
      "",
      "",
      "",
      "",
      "",
      "",
      "",
      "",
      "",
      "",
      "",
      "",
      "",
      "",
      "",
      "",
      "",
      "",
      "",
      "",
      "",
      "",
      "",
      "",
      "",
      "",
      "",
      "",
      "",
      "",
      "",
      "",
      "",
      "",
      "",
      "",
      "",
      "",
      "",
      "",
      "",
      "",
      "",
      "",
      "",
      "",
      "",
      "",
      "",
      "",
      "",
      "",
      "",
      "",
      "",
      "",
      "",
      "",
      "",
      "",
      "",
      "",
      "",
      "",
      "",
      "",
      "",
      "",
      "",
      "",
      "",
      ""
    ],
    "values": [
      0,
      0,
      0,
      0,
      0,
      0,
      0,
      0,
      0,
      0,
      0,
      0,
      0,
      0,
      0,
      0,
      0,
      0,
      0,
      0,
      0,
      0,
      0,
      0,
      0.009999999776482582,
      0,
      0,
      0,
      0,
      0,
      0,
      0,
      0,
      0,
      0,
      0,
      0,
      0.009999999776482582,
      0,
      0,
      0,
      0,
      0,
      0,
      0,
      0,
      0,
      0,
      0,
      0,
      0,
      0,
      0,
      0,
      0,
      0,
      0,
      0,
      0,
      0.019999999552965164,
      0,
      0,
      0,
      0,
      0.009999999776482582,
      0.009999999776482582,
      0.009999999776482582,
      0.019999999552965164,
      0.009999999776482582,
      0.019999999552965164,
      0.029999999329447746,
      0.03999999910593033,
      0.03999999910593033,
      0.019999999552965164,
      0.009999999776482582,
      0.05000000074505806,
      0.03999999910593033,
      0.019999999552965164,
      0.03999999910593033,
      0.009999999776482582,
      0.009999999776482582,
      0.12999999523162842,
      0.029999999329447746,
      0.05999999865889549,
      0.09000000357627869,
      0.009999999776482582,
      0.05000000074505806,
      0.05000000074505806,
      0.05999999865889549,
      0.1899999976158142,
      0.05999999865889549,
      0.09000000357627869,
      0.14000000059604645,
      0.10999999940395355,
      0.20000000298023224,
      0.15000000596046448,
      0.10000000149011612,
      0.1599999964237213,
      0.11999999731779099,
      0.15000000596046448,
      0.4099999964237213,
      0.2199999988079071,
      0.28999999165534973,
      0.25,
      0.2800000011920929,
      0.4099999964237213,
      0.27000001072883606,
      0.25999999046325684,
      0.1899999976158142,
      0.2199999988079071,
      0.23999999463558197,
      0.09000000357627869,
      0.27000001072883606,
      0.25,
      0.1599999964237213,
      0.1599999964237213,
      0.3100000023841858,
      0.2199999988079071,
      0.25999999046325684,
      0.4399999976158142,
      0.20000000298023224
    ]
  },
  "eval_average_return": {
    "steps": [
      0,
      9,
      19,
      29,
      39,
      49,
      59,
      69,
      79,
      89,
      99,
      109,
      119,
      129,
      139,
      149,
      159,
      169,
      179,
      189,
      199,
      209,
      219,
      229,
      239,
      249,
      259,
      269,
      279,
      289,
      299,
      309,
      319,
      329,
      339,
      349,
      359,
      369,
      379,
      389,
      399,
      409,
      419,
      429,
      439,
      449,
      459,
      469,
      479,
      489,
      499,
      509,
      519,
      529,
      539,
      549,
      559,
      569,
      579,
      589,
      599,
      609,
      619,
      629,
      639,
      649,
      659,
      669,
      679,
      689,
      699,
      709,
      719,
      729,
      739,
      749,
      759,
      769,
      779,
      789,
      799,
      809,
      819,
      829,
      839,
      849,
      859,
      869,
      879,
      889,
      899,
      909,
      919,
      929,
      939,
      949,
      959,
      969,
      979,
      989,
      999,
      1009,
      1019,
      1029,
      1039,
      1049,
      1059,
      1069,
      1079,
      1089,
      1099,
      1109,
      1119,
      1129,
      1139,
      1149,
      1159,
      1169,
      1179,
      1189,
      1199
    ],
    "timestamps": [
      "",
      "",
      "",
      "",
      "",
      "",
      "",
      "",
      "",
      "",
      "",
      "",
      "",
      "",
      "",
      "",
      "",
      "",
      "",
      "",
      "",
      "",
      "",
      "",
      "",
      "",
      "",
      "",
      "",
      "",
      "",
      "",
      "",
      "",
      "",
      "",
      "",
      "",
      "",
      "",
      "",
      "",
      "",
      "",
      "",
      "",
      "",
      "",
      "",
      "",
      "",
      "",
      "",
      "",
      "",
      "",
      "",
      "",
      "",
      "",
      "",
      "",
      "",
      "",
      "",
      "",
      "",
      "",
      "",
      "",
      "",
      "",
      "",
      "",
      "",
      "",
      "",
      "",
      "",
      "",
      "",
      "",
      "",
      "",
      "",
      "",
      "",
      "",
      "",
      "",
      "",
      "",
      "",
      "",
      "",
      "",
      "",
      "",
      "",
      "",
      "",
      "",
      "",
      "",
      "",
      "",
      "",
      "",
      "",
      "",
      "",
      "",
      "",
      "",
      "",
      "",
      "",
      "",
      "",
      "",
      ""
    ],
    "values": [
      0,
      0,
      0,
      0,
      0,
      0,
      0,
      0,
      0,
      0.009999999776482582,
      0,
      0.03999999910593033,
      0.12999999523162842,
      0.029999999329447746,
      0.12999999523162842,
      0.07999999821186066,
      0.07999999821186066,
      0.15000000596046448,
      0.20999999344348907,
      0.18000000715255737,
      0.36000001430511475,
      0.33000001311302185,
      0.09000000357627869,
      0.20000000298023224,
      0.09000000357627869,
      0.20999999344348907,
      0.47999998927116394,
      0.5299999713897705,
      0.15000000596046448,
      0.28999999165534973,
      0.23999999463558197,
      0.2199999988079071,
      0.49000000953674316,
      0.25,
      0.28999999165534973,
      0.38999998569488525,
      0.46000000834465027,
      0.36000001430511475,
      0.49000000953674316,
      0.3499999940395355,
      0.23999999463558197,
      0.25999999046325684,
      0.3700000047683716,
      0.33000001311302185,
      0.5199999809265137,
      0.38999998569488525,
      0.09000000357627869,
      0.23999999463558197,
      0.5,
      0.3799999952316284,
      0.4399999976158142,
      0.4699999988079071,
      0.3199999928474426,
      0.5099999904632568,
      0.47999998927116394,
      0.5099999904632568,
      0.4000000059604645,
      0.38999998569488525,
      0.4000000059604645,
      0.5299999713897705,
      0.6200000047683716,
      0.4099999964237213,
      0.4300000071525574,
      0.5,
      0.5600000023841858,
      0.6000000238418579,
      0.6100000143051147,
      0.6200000047683716,
      0.6399999856948853,
      0.4699999988079071,
      0.5,
      0.4699999988079071,
      0.6299999952316284,
      0.6700000166893005,
      0.5699999928474426,
      0.6499999761581421,
      0.49000000953674316,
      0.49000000953674316,
      0.550000011920929,
      0.6899999976158142,
      0.5299999713897705,
      0.6200000047683716,
      0.46000000834465027,
      0.699999988079071,
      0.6000000238418579,
      0.6600000262260437,
      0.6499999761581421,
      0.6700000166893005,
      0.6499999761581421,
      0.7300000190734863,
      0.699999988079071,
      0.6100000143051147,
      0.6299999952316284,
      0.6700000166893005,
      0.6800000071525574,
      0.6600000262260437,
      0.6499999761581421,
      0.6800000071525574,
      0.6000000238418579,
      0.6600000262260437,
      0.6299999952316284,
      0.7099999785423279,
      0.6800000071525574,
      0.7300000190734863,
      0.7300000190734863,
      0.6399999856948853,
      0.6800000071525574,
      0.5799999833106995,
      0.7099999785423279,
      0.6399999856948853,
      0.5899999737739563,
      0.6499999761581421,
      0.6499999761581421,
      0.5799999833106995,
      0.5600000023841858,
      0.6200000047683716,
      0.6499999761581421,
      0.6700000166893005,
      0.7300000190734863,
      0.699999988079071,
      0.7300000190734863
    ]
  },
  "action_gap": {
    "steps": [
      0,
      9,
      19,
      29,
      39,
      49,
      59,
      69,
      79,
      89,
      99,
      109,
      119,
      129,
      139,
      149,
      159,
      169,
      179,
      189,
      199,
      209,
      219,
      229,
      239,
      249,
      259,
      269,
      279,
      289,
      299,
      309,
      319,
      329,
      339,
      349,
      359,
      369,
      379,
      389,
      399,
      409,
      419,
      429,
      439,
      449,
      459,
      469,
      479,
      489,
      499,
      509,
      519,
      529,
      539,
      549,
      559,
      569,
      579,
      589,
      599,
      609,
      619,
      629,
      639,
      649,
      659,
      669,
      679,
      689,
      699,
      709,
      719,
      729,
      739,
      749,
      759,
      769,
      779,
      789,
      799,
      809,
      819,
      829,
      839,
      849,
      859,
      869,
      879,
      889,
      899,
      909,
      919,
      929,
      939,
      949,
      959,
      969,
      979,
      989,
      999,
      1009,
      1019,
      1029,
      1039,
      1049,
      1059,
      1069,
      1079,
      1089,
      1099,
      1109,
      1119,
      1129,
      1139,
      1149,
      1159,
      1169,
      1179,
      1189,
      1199
    ],
    "timestamps": [
      "",
      "",
      "",
      "",
      "",
      "",
      "",
      "",
      "",
      "",
      "",
      "",
      "",
      "",
      "",
      "",
      "",
      "",
      "",
      "",
      "",
      "",
      "",
      "",
      "",
      "",
      "",
      "",
      "",
      "",
      "",
      "",
      "",
      "",
      "",
      "",
      "",
      "",
      "",
      "",
      "",
      "",
      "",
      "",
      "",
      "",
      "",
      "",
      "",
      "",
      "",
      "",
      "",
      "",
      "",
      "",
      "",
      "",
      "",
      "",
      "",
      "",
      "",
      "",
      "",
      "",
      "",
      "",
      "",
      "",
      "",
      "",
      "",
      "",
      "",
      "",
      "",
      "",
      "",
      "",
      "",
      "",
      "",
      "",
      "",
      "",
      "",
      "",
      "",
      "",
      "",
      "",
      "",
      "",
      "",
      "",
      "",
      "",
      "",
      "",
      "",
      "",
      "",
      "",
      "",
      "",
      "",
      "",
      "",
      "",
      "",
      "",
      "",
      "",
      "",
      "",
      "",
      "",
      "",
      "",
      ""
    ],
    "values": [
      3.0337061882019043,
      2.4174129962921143,
      2.376526117324829,
      2.38638973236084,
      2.4103941917419434,
      2.4499685764312744,
      2.5199007987976074,
      2.6333673000335693,
      2.7508139610290527,
      2.6501755714416504,
      2.691624641418457,
      2.7338125705718994,
      2.7330706119537354,
      2.7006349563598633,
      2.7582955360412598,
      2.752080202102661,
      2.7569186687469482,
      2.639436721801758,
      2.7061192989349365,
      2.6973249912261963,
      2.7167348861694336,
      2.632154703140259,
      2.5757856369018555,
      2.661175489425659,
      2.588601589202881,
      2.7522354125976562,
      2.709681272506714,
      2.7063281536102295,
      2.6913506984710693,
      2.640585422515869,
      2.6318857669830322,
      2.6730196475982666,
      2.6807920932769775,
      2.723526954650879,
      2.7349371910095215,
      2.7623748779296875,
      2.746943235397339,
      2.695920944213867,
      2.7429966926574707,
      2.754218339920044,
      2.762533664703369,
      2.7633719444274902,
      2.72672176361084,
      2.762421131134033,
      2.7572758197784424,
      2.8193893432617188,
      2.8127782344818115,
      2.8097715377807617,
      2.796050786972046,
      2.848317861557007,
      2.85158371925354,
      2.8197097778320312,
      2.8038527965545654,
      2.8097245693206787,
      2.838327407836914,
      2.839256763458252,
      2.873802900314331,
      2.878382682800293,
      2.8207592964172363,
      2.7889273166656494,
      2.874589204788208,
      2.8874948024749756,
      2.8804385662078857,
      2.895681619644165,
      2.8499131202697754,
      2.699904680252075,
      2.87575101852417,
      2.9105539321899414,
      2.7209312915802,
      2.7623255252838135,
      2.851022720336914,
      3.0135910511016846,
      2.8148398399353027,
      2.7778265476226807,
      2.82279634475708,
      2.8693408966064453,
      2.8020174503326416,
      2.8070120811462402,
      2.8914432525634766,
      2.7794079780578613,
      2.849843740463257,
      3.0889573097229004,
      2.9825141429901123,
      2.9674904346466064,
      2.8836770057678223,
      2.915048122406006,
      2.910031318664551,
      2.8586716651916504,
      2.854738473892212,
      2.9486050605773926,
      2.9037821292877197,
      2.906550884246826,
      3.1289446353912354,
      2.882553815841675,
      3.0118134021759033,
      3.1251471042633057,
      2.9190540313720703,
      2.898275136947632,
      2.949465274810791,
      2.9347124099731445,
      2.9459195137023926,
      2.935143232345581,
      2.9132778644561768,
      2.814138889312744,
      2.916233539581299,
      2.974050521850586,
      2.9105050563812256,
      2.736769437789917,
      2.8537511825561523,
      2.9637715816497803,
      2.994621992111206,
      3.001936912536621,
      2.904966354370117,
      2.8945937156677246,
      2.9627866744995117,
      3.0045180320739746,
      2.872626304626465,
      2.9184916019439697,
      2.9116814136505127,
      3.001493453979492,
      2.864943265914917
    ]
  }
}